{
  "name": "Cordelia Price",
  "age": 20,
  "address": {
    "street": "Jaaca Plaza",
    "city": "Viwatic",
    "state": "ID",
    "zip": "38598"
  },
  "contact": {
    "phone": "(623) 413-1564",
    "servicePhone": "800726935"
  },
  "birthday": "1986-03-29T14:26:10.118Z",
  "ip": "62.218.212.136",
  "foo": "bar",
  "profile": {
    "about": "Bupitge kav ginzab comam nedhe ipzeg ifu bar jupecal fin kisko jujfivu dupbi bener vaowukoc tasbe iwe. Nahwuwgal opilehid kuj cirriwhe fodsom nijhidoc not nigkazaso le pal tefmew mega. Fo az tedaj lima okzujle zu duwgi div zolpol erufa tunhagu mahih. Ma gugileka fum fad ef tungeju cerudjez buctafufo os vuh ge va zon bomotme wovvuh ewtaale cufmiboj.",
    "bio": "Fi uli ufji wek metdod jutror muceaso ugivuh papom votesi raocodas gu hel dowitfi gipjon pe fif. Awmug fiwic remba dovvek natkansum vu gokju le zibve cez pon tawe. Wi ut di daltifged ozavervo fecesaj galnufko mavvas gakguuku ekavo jiobizam elhidol. Nag inlap getkose am te vum ucaazo ragube evvopcac zep matitom cursam fug kaltugig pijirad top owiwewpeg. Fur tovgo na zuhra wamabo po simvo boj vegu res bojbidcez duddo boco jehowa. Ama dippoefi bencif pe vo can kiznunozu tugup sa duc adeepun gezcupez. Gegujat bekpafow dak efuwbo he fik itpelrij zubipfu lam musodo ekimolvip cethewwe novci."
  },
  "apiKey": "1cf354ea9cd91b868e6122d2d2ab0e33e51c88ada550ba37d0fea50fa27844ec",
  "currency": {
    "code": "CDF",
    "name": "Congo/Kinshasa Franc"
  }
}