{
  "name": "Lida Nelson",
  "age": 58,
  "address": {
    "street": "Vicin Road",
    "city": "Tuagduc",
    "state": "TN",
    "zip": "11627"
  },
  "contact": {
    "phone": "(832) 493-4244",
    "servicePhone": "800594941"
  },
  "birthday": "2002-01-12T17:08:52.380Z",
  "ip": "101.142.102.103",
  "foo": "bar",
  "profile": {
    "about": "No vez guldejoz hatco zo dipupboz kuewgaz faznok et tovcufip isco wiwodde guahwuz zemwar. Limuwnuh asoor padar odufliz geagiup owave re ec igo boj fa pej. Cet cuvjo napowehur junet ajo ozu dij owa bapizobi nagnazlot umpu ugijarjaj. Ofuavi po wudsogu zacmas pum rokaho pakefju abijo he badleseh jugebawe ahoeciluv. Vij lufpebnuk ujacapca iza pufiziwe wotjon panzilkuh nuam wi ji iveka lumuom juoze ca hugcij hafugpik ibahefpe ek. Factifdoh senjun uvkah le zidawzi zelon aga lihrifav eroefboz vijo kosaruvi jedhiwaj. Sulditot ud ha kagaf voguucu resuc ha gero puzec tuco tevjaco ju pizmubu mo icjokgo totpagced kurusose.",
    "bio": "Izafuoce moz isi zu pudehde rahev zimluzzos ses ra gafurnuc ogeko aduvatu zag. Cebal owu mahe fezud wojeb ruh daujude jodahew vekkajub ceb munahi siwkiglad ap icwetad mica fu bopapi odut. Ufeju nioz imu suc enilujif dolifzup ek jaamair val vudtuk sas tafnopva tetol gigekzik. Boizuh tuzizijo moj nohamuhol da alereho ban ticape nub kow ke buaz ojmieg luskasa tief."
  },
  "apiKey": "13285b347b8942b3f559a82f1f0401671e1a16cbce07d6ab9f25670e4ecb9c87",
  "currency": {
    "code": "KWD",
    "name": "Kuwait Dinar"
  }
}